toni/__init__.py
toni/cli.py
toni/core.py
toni/test.py
toni_cli-0.1.16.dist-info/licenses/LICENSE
toni_cli-0.1.16.dist-info/METADATA
toni_cli-0.1.16.dist-info/WHEEL
toni_cli-0.1.16.dist-info/entry_points.txt
toni_cli-0.1.16.dist-info/top_level.txt
toni_cli-0.1.16.dist-info/RECORD
