Metadata-Version: 2.4
Name: toni-cli
Version: 0.1.16
Summary: Terminal Operation Natural Instruction - AI-powered terminal assistant
Author-email: Dakai Ou <oudakai@gmail.com>
License-Expression: MIT
Project-URL: Homepage, https://github.com/dakai/toni
Project-URL: Bug Tracker, https://github.com/dakai/toni/issues
Classifier: Programming Language :: Python :: 3
Classifier: Operating System :: OS Independent
Requires-Python: >=3.10
License-File: LICENSE
Requires-Dist: openai>=1.66.3
Requires-Dist: google-genai>=1.5.0
Requires-Dist: mistralai>=1.7.0
Requires-Dist: termcolor>=3.1.0
Dynamic: license-file
